CHANGES
INSTALL
MANIFEST.in
Makefile
README
TODO
bootstrap
setup.cfg
setup.py
.hg/store/data/admin/_p_k_g-_i_n_f_o.in.i
.hg/store/data/admin/static/classifiers.txt.i
.hg/store/data/admin/static/copyright.txt.i
.hg/store/data/examples/contrib/django/contrib/admin/____init____.py.i
.hg/store/data/examples/contrib/django/contrib/admin/actions.py.i
.hg/store/data/examples/contrib/django/contrib/admin/filterspecs.py.i
.hg/store/data/examples/contrib/django/contrib/admin/helpers.py.i
.hg/store/data/examples/contrib/django/contrib/admin/models.py.i
.hg/store/data/examples/contrib/django/contrib/admin/options.py.i
.hg/store/data/examples/contrib/django/contrib/admin/sites.py.i
.hg/store/data/examples/contrib/django/contrib/admin/util.py.i
.hg/store/data/examples/contrib/django/contrib/admin/validation.py.i
.hg/store/data/examples/contrib/django/contrib/admin/widgets.py.i
.hg/store/data/examples/contrib/django/contrib/admin/media/img/admin/arrow-down.gif.i
.hg/store/data/examples/contrib/django/contrib/admin/media/img/admin/arrow-up.gif.i
.hg/store/data/examples/contrib/django/contrib/admin/media/img/admin/changelist-bg.gif.i
.hg/store/data/examples/contrib/django/contrib/admin/media/img/admin/changelist-bg__rtl.gif.i
.hg/store/data/examples/contrib/django/contrib/admin/media/img/admin/chooser-bg.gif.i
.hg/store/data/examples/contrib/django/contrib/admin/media/img/admin/chooser__stacked-bg.gif.i
.hg/store/data/examples/contrib/django/contrib/admin/media/img/admin/default-bg-reverse.gif.i
.hg/store/data/examples/contrib/django/contrib/admin/media/img/admin/default-bg.gif.i
.hg/store/data/examples/contrib/django/contrib/admin/media/img/admin/deleted-overlay.gif.i
.hg/store/data/examples/contrib/django/contrib/admin/media/img/admin/icon-no.gif.i
.hg/store/data/examples/contrib/django/contrib/admin/media/img/admin/icon-unknown.gif.i
.hg/store/data/examples/contrib/django/contrib/admin/media/img/admin/icon-yes.gif.i
lib/django_hotsauce.egg-info/PKG-INFO
lib/django_hotsauce.egg-info/SOURCES.txt
lib/django_hotsauce.egg-info/dependency_links.txt
lib/django_hotsauce.egg-info/not-zip-safe
lib/django_hotsauce.egg-info/requires.txt
lib/django_hotsauce.egg-info/top_level.txt
